LICENSE
MANIFEST.in
README.rst
setup.py
pyrecorder/__init__.py
pyrecorder/converter.py
pyrecorder/recorder.py
pyrecorder/scratch.py
pyrecorder/version.py
pyrecorder/writer.py
pyrecorder.egg-info/PKG-INFO
pyrecorder.egg-info/SOURCES.txt
pyrecorder.egg-info/dependency_links.txt
pyrecorder.egg-info/requires.txt
pyrecorder.egg-info/top_level.txt
pyrecorder/converters/__init__.py
pyrecorder/converters/matplotlib.py
pyrecorder/experimental/__init__.py
pyrecorder/experimental/html.py
pyrecorder/experimental/plotly.py
pyrecorder/writers/__init__.py
pyrecorder/writers/gif.py
pyrecorder/writers/streamer.py
pyrecorder/writers/video.py