Metadata-Version: 1.2
Name: pyrecorder
Version: 0.2.1
Summary: Recorder Recording made easy - The tool you need for animations using Matplotlib, Plotly and other plotting libraries. 
Home-page: https://anyoptimization.com/projects/pyrecorder/
Author: Julian Blank
Author-email: blankjul@egr.msu.edu
License: Apache License 2.0
Keywords: video,recording,matplotlib,plotly
Platform: any
Classifier: Intended Audience :: Developers
Classifier: Intended Audience :: Science/Research
Classifier: Operating System :: OS Independent
Classifier: License :: OSI Approved :: Apache Software License
Classifier: Programming Language :: Python
Classifier: Programming Language :: Python :: 3
Classifier: Programming Language :: Python :: 3.6
Classifier: Programming Language :: Python :: 3.7
Classifier: Programming Language :: Python :: 3.8
Classifier: Programming Language :: Python :: 3.9
Classifier: Topic :: Scientific/Engineering :: Visualization
Requires-Python: >=3.6
